napari_imagegrains/__init__.py
napari_imagegrains/_version.py
napari_imagegrains/access_single_image_widget.py
napari_imagegrains/folder_list_widget.py
napari_imagegrains/imgr_demodata_widget.py
napari_imagegrains/imgr_proc_widget.py
napari_imagegrains/imgr_stats_widget.py
napari_imagegrains/napari.yaml
napari_imagegrains/utils.py
napari_imagegrains/_tests/__init__.py
napari_imagegrains/_tests/ipynb_to_py.py
napari_imagegrains/_tests/test_1_Demo_widget.py
napari_imagegrains/_tests/test_2_1_Processing_widget_segmentation_tab.py
napari_imagegrains/_tests/test_2_2_Processing_widget_performance_tab.py
napari_imagegrains/_tests/test_3_1_Stats_widget_properties_tab.py
napari_imagegrains/_tests/test_3_2_Stats_widget_grain_size_tab.py
napari_imagegrains-1.0.0.dist-info/licenses/LICENSE
napari_imagegrains-1.0.0.dist-info/METADATA
napari_imagegrains-1.0.0.dist-info/WHEEL
napari_imagegrains-1.0.0.dist-info/entry_points.txt
napari_imagegrains-1.0.0.dist-info/top_level.txt
napari_imagegrains-1.0.0.dist-info/RECORD
