Metadata-Version: 2.4
Name: napari-imagegrains
Version: 1.0.0
Summary: An interactive napari plugin for the ImageGrains software.
Author-email: Guillaume Witz <guillaume.witz@unibe.ch>, Michael Horn <michael.horn@unibe.ch>
License: 
Project-URL: Bug Tracker, https://github.com/guiwitz/napari-imagegrains/issues
Project-URL: Documentation, https://github.com/guiwitz/napari-imagegrains#README.md
Project-URL: Source Code, https://github.com/guiwitz/napari-imagegrains
Project-URL: User Support, https://github.com/guiwitz/napari-imagegrains/issues
Classifier: Development Status :: 2 - Pre-Alpha
Classifier: Framework :: napari
Classifier: Intended Audience :: Developers
Classifier: License :: OSI Approved :: BSD License
Classifier: Operating System :: OS Independent
Classifier: Programming Language :: Python
Classifier: Programming Language :: Python :: 3
Classifier: Programming Language :: Python :: 3 :: Only
Classifier: Programming Language :: Python :: 3.9
Classifier: Programming Language :: Python :: 3.10
Classifier: Programming Language :: Python :: 3.11
Classifier: Topic :: Scientific/Engineering :: Image Processing
Requires-Python: >=3.9
License-File: LICENSE
Requires-Dist: numpy<=2.2
Requires-Dist: magicgui
Requires-Dist: qtpy
Requires-Dist: superqt
Requires-Dist: napari_matplotlib
Requires-Dist: scikit-image
Requires-Dist: seaborn
Requires-Dist: pandas
Requires-Dist: imagegrains>=1.2.0
Provides-Extra: testing
Requires-Dist: tox; extra == "testing"
Requires-Dist: pytest; extra == "testing"
Requires-Dist: pytest-cov; extra == "testing"
Requires-Dist: pytest-qt; extra == "testing"
Requires-Dist: pyqt5; extra == "testing"
Requires-Dist: napari; extra == "testing"
Requires-Dist: nbformat; extra == "testing"
Requires-Dist: nbconvert; extra == "testing"
Dynamic: license-file
